picopayments_cli/__init__.py
picopayments_cli/api.py
picopayments_cli/auth.py
picopayments_cli/cli.py
picopayments_cli/etc.py
picopayments_cli/mpc.py
picopayments_cli/mph.py
picopayments_cli/parse.py
picopayments_cli/rpc.py
picopayments_cli/version.py
picopayments_cli/bin/picopayments-cli
picopayments_cli-1.0.4.data/scripts/picopayments-cli
picopayments_cli-1.0.4.dist-info/DESCRIPTION.rst
picopayments_cli-1.0.4.dist-info/METADATA
picopayments_cli-1.0.4.dist-info/RECORD
picopayments_cli-1.0.4.dist-info/WHEEL
picopayments_cli-1.0.4.dist-info/metadata.json
picopayments_cli-1.0.4.dist-info/top_level.txt
tests/__init__.py
tests/auth_test.py
tests/mock_rpc_server.py
tests/rpc_test.py
