Metadata-Version: 2.0
Name: picopayments-cli
Version: 1.0.4
Summary: Micropayment hub client for counterparty assets.
Home-page: http://storj.io
Author: Fabian Barkhau
Author-email: f483@storj.io
License: MIT
Keywords: storj,counterparty,micropayment,client
Platform: UNKNOWN
Classifier: Development Status :: 2 - Pre-Alpha
Classifier: Intended Audience :: Developers
Classifier: License :: OSI Approved :: MIT License
Classifier: Operating System :: OS Independent
Classifier: Programming Language :: Python
Classifier: Programming Language :: Python :: 2
Classifier: Programming Language :: Python :: 2.7
Classifier: Programming Language :: Python :: 3
Classifier: Programming Language :: Python :: 3.3
Classifier: Programming Language :: Python :: 3.4
Classifier: Topic :: Software Development :: Libraries :: Python Modules
Requires-Dist: Werkzeug (==0.11.15)
Requires-Dist: future (==0.16.0)
Requires-Dist: json-rpc (==1.10.3)
Requires-Dist: micropayment-core (==1.0.1)
Requires-Dist: pyelliptic (==1.5.7)
Requires-Dist: requests (==2.10.0)
